easybill_client/__init__.py
easybill_client/client.py
easybill_client/models.py
easybill_api_client-0.1.0.dist-info/METADATA
easybill_api_client-0.1.0.dist-info/WHEEL
easybill_api_client-0.1.0.dist-info/licenses/LICENSE
easybill_api_client-0.1.0.dist-info/RECORD
