Metadata-Version: 2.4
Name: easybill-api-client
Version: 0.1.0
Summary: Python client for the Easybill REST API
Project-URL: Homepage, https://github.com/dkd-dobberkau/easybill-api-client
Project-URL: Repository, https://github.com/dkd-dobberkau/easybill-api-client
Project-URL: Issues, https://github.com/dkd-dobberkau/easybill-api-client/issues
Author-email: Olivier Dobberkau <olivier.dobberkau@dkd.de>
License: MIT
License-File: LICENSE
Keywords: api,client,easybill,invoicing
Classifier: Development Status :: 4 - Beta
Classifier: Intended Audience :: Developers
Classifier: License :: OSI Approved :: MIT License
Classifier: Programming Language :: Python :: 3
Classifier: Programming Language :: Python :: 3.11
Classifier: Programming Language :: Python :: 3.12
Classifier: Topic :: Office/Business :: Financial :: Accounting
Requires-Python: >=3.11
Requires-Dist: easybill-rest>=0.6.0
Requires-Dist: pydantic>=2.0.0
Provides-Extra: dev
Requires-Dist: pytest-cov>=4.0.0; extra == 'dev'
Requires-Dist: pytest>=8.0.0; extra == 'dev'
Requires-Dist: ruff>=0.1.0; extra == 'dev'
